smartspace/__init__.py
smartspace/__main__.py
smartspace/blocks/__init__.py
smartspace/blocks/buffer.py
smartspace/blocks/cast_block.py
smartspace/blocks/conditionals.py
smartspace/blocks/const_blocks.py
smartspace/blocks/google_search.py
smartspace/blocks/http/http_1_0_0.py
smartspace/blocks/http/http_2_0_0.py
smartspace/blocks/json_blocks.py
smartspace/blocks/lists.py
smartspace/blocks/loops.py
smartspace/blocks/regex_match.py
smartspace/blocks/sql.py
smartspace/blocks/string_template.py
smartspace/blocks/strings.py
smartspace/blocks/template_object.py
smartspace/blocks/truncate_string.py
smartspace/blocks/type_switch.py
smartspace/blocks/variable.py
smartspace/blocks/website_scraper.py
smartspace/cli/__init__.py
smartspace/cli/app.py
smartspace/cli/auth.py
smartspace/cli/blocks.py
smartspace/cli/config.py
smartspace/cli/models.py
smartspace/core.py
smartspace/enums.py
smartspace/models.py
smartspace/py.typed
smartspace/tests/test_http_blocks.py
smartspace/tests/test_regex_match_block.py
smartspace/tests/test_tool_channel_close.py
smartspace/tests/test_truncate_string.py
smartspace/tests/test_website_scraper.py
smartspace/utils/__init__.py
smartspace/utils/expressions.py
smartspace/utils/utils.py
smartspace_ai-0.1.8.dist-info/METADATA
smartspace_ai-0.1.8.dist-info/WHEEL
smartspace_ai-0.1.8.dist-info/entry_points.txt
smartspace_ai-0.1.8.dist-info/RECORD
