Metadata-Version: 2.1
Name: smartspace-ai
Version: 0.1.8
Summary: Smartspace SDK
Author: David Gentile
Author-email: david.gentile@smartspace.ai
Requires-Python: >=3.10,<3.12
Classifier: Programming Language :: Python :: 3
Classifier: Programming Language :: Python :: 3.10
Classifier: Programming Language :: Python :: 3.11
Requires-Dist: aiomysql (>=0.2.0,<0.3.0)
Requires-Dist: aioodbc (>=0.5.0,<0.6.0)
Requires-Dist: annotated-types (==0.5.0)
Requires-Dist: azure-identity (>=1.17.1,<2.0.0)
Requires-Dist: docxtpl (>=0.19.0,<0.20.0)
Requires-Dist: httpx (>=0.27.0,<0.28.0)
Requires-Dist: jsonpath-ng (>=1.6.1,<2.0.0)
Requires-Dist: jsonschema (>=4.23.0,<5.0.0)
Requires-Dist: lark (>=1.2.2,<2.0.0)
Requires-Dist: litellm (>=1.43.19,<2.0.0)
Requires-Dist: llama-index (>=0.12.42,<0.13.0)
Requires-Dist: llama-index-embeddings-huggingface (>=0.5.4,<0.6.0)
Requires-Dist: more-itertools (>=10.3.0,<11.0.0)
Requires-Dist: msal (>=1.29.0,<2.0.0)
Requires-Dist: mypy (>=1.8.0,<2.0.0)
Requires-Dist: mypy-extensions (==1.0.0)
Requires-Dist: neo4j (>=5.24.0,<6.0.0)
Requires-Dist: numpy (>=1.26.0,<2.0.0)
Requires-Dist: pandoc (>=2.4,<3.0)
Requires-Dist: pydantic (==2.8.0)
Requires-Dist: pydantic-extra-types (==2.0.0)
Requires-Dist: pydantic-settings (==2.0.3)
Requires-Dist: pyodbc (>=5.2.0,<6.0.0)
Requires-Dist: pypandoc (>=1.14,<2.0)
Requires-Dist: pysignalr (>=1.0.0,<2.0.0)
Requires-Dist: python-docx (>=1.1.2,<2.0.0)
Requires-Dist: semantic-version (>=2.10.0,<3.0.0)
Requires-Dist: sqlalchemy (>=2.0.36,<3.0.0)
Requires-Dist: typer (==0.16.0)
Requires-Dist: types-requests (>=2.32.0.20240914,<3.0.0.0)
Requires-Dist: watchdog (==4.0.1)
